{
  "code": "000000",
  "message": null,
  "messageDetail": null,
  "data": [
    {
      "tradeId": 255387307,
      "price": "1234.62",
      "time": 1610672336000,
      "symbol": "ETHUSDT",
      "side": "SELL",
      "activeBuy": false,
      "realPnl": 0,
      "qty": "0.01197",
      "fee": "0.01477840",
      "feeAsset": "USDT",
      "totalQuota": "14.77840140",
      "productName": null,
      "baseAsset": "ETH",
      "quoteAsset": "USDT",
      "money": null,
      "userId": 35345229,
      "email": null
    },
    {
      "tradeId": 255387254,
      "price": "1234.58",
      "time": 1610672331000,
      "symbol": "ETHUSDT",
      "side": "SELL",
      "activeBuy": false,
      "realPnl": 0,
      "qty": "0.00900",
      "fee": "0.01111122",
      "feeAsset": "USDT",
      "totalQuota": "11.11122000",
      "productName": null,
      "baseAsset": "ETH",
      "quoteAsset": "USDT",
      "money": null,
      "userId": 35345229,
      "email": null
    },
    {
      "tradeId": 255387181,
      "price": "1234.72",
      "time": 1610672320000,
      "symbol": "ETHUSDT",
      "side": "SELL",
      "activeBuy": false,
      "realPnl": 0,
      "qty": "0.00891",
      "fee": "0.01100136",
      "feeAsset": "USDT",
      "totalQuota": "11.00135520",
      "productName": null,
      "baseAsset": "ETH",
      "quoteAsset": "USDT",
      "money": null,
      "userId": 35345229,
      "email": null
    },
    {
      "tradeId": 255387180,
      "price": "1234.72",
      "time": 1610672320000,
      "symbol": "ETHUSDT",
      "side": "SELL",
      "activeBuy": false,
      "realPnl": 0,
      "qty": "0.00009",
      "fee": "0.00011112",
      "feeAsset": "USDT",
      "totalQuota": "0.11112480",
      "productName": null,
      "baseAsset": "ETH",
      "quoteAsset": "USDT",
      "money": null,
      "userId": 35345229,
      "email": null
    },
    {
      "tradeId": 254592443,
      "price": "1148.00",
      "time": 1610626993000,
      "symbol": "ETHUSDT",
      "side": "BUY",
      "activeBuy": false,
      "realPnl": 0,
      "qty": "0.01000",
      "fee": "0.00001000",
      "feeAsset": "ETH",
      "totalQuota": "11.48000000",
      "productName": null,
      "baseAsset": "ETH",
      "quoteAsset": "USDT",
      "money": null,
      "userId": 35345229,
      "email": null
    },
    {
      "tradeId": 254592209,
      "price": "1149.00",
      "time": 1610626989000,
      "symbol": "ETHUSDT",
      "side": "BUY",
      "activeBuy": false,
      "realPnl": 0,
      "qty": "0.01000",
      "fee": "0.00001000",
      "feeAsset": "ETH",
      "totalQuota": "11.49000000",
      "productName": null,
      "baseAsset": "ETH",
      "quoteAsset": "USDT",
      "money": null,
      "userId": 35345229,
      "email": null
    },
    {
      "tradeId": 254590907,
      "price": "1150.37",
      "time": 1610626950000,
      "symbol": "ETHUSDT",
      "side": "BUY",
      "activeBuy": false,
      "realPnl": 0,
      "qty": "0.01000",
      "fee": "0.00001000",
      "feeAsset": "ETH",
      "totalQuota": "11.50370000",
      "productName": null,
      "baseAsset": "ETH",
      "quoteAsset": "USDT",
      "money": null,
      "userId": 35345229,
      "email": null
    },
    {
      "tradeId": 254497306,
      "price": "1153.00",
      "time": 1610618595000,
      "symbol": "ETHUSDT",
      "side": "SELL",
      "activeBuy": true,
      "realPnl": 0,
      "qty": "0.07432",
      "fee": "0.08569096",
      "feeAsset": "USDT",
      "totalQuota": "85.69096000",
      "productName": null,
      "baseAsset": "ETH",
      "quoteAsset": "USDT",
      "money": null,
      "userId": 35345229,
      "email": null
    },
    {
      "tradeId": 254425746,
      "price": "1157.00",
      "time": 1610612533000,
      "symbol": "ETHUSDT",
      "side": "BUY",
      "activeBuy": false,
      "realPnl": 0,
      "qty": "0.01440",
      "fee": "0.00001440",
      "feeAsset": "ETH",
      "totalQuota": "16.66080000",
      "productName": null,
      "baseAsset": "ETH",
      "quoteAsset": "USDT",
      "money": null,
      "userId": 35345229,
      "email": null
    },
    {
      "tradeId": 254425468,
      "price": "1158.00",
      "time": 1610612531000,
      "symbol": "ETHUSDT",
      "side": "BUY",
      "activeBuy": false,
      "realPnl": 0,
      "qty": "0.01000",
      "fee": "0.00001000",
      "feeAsset": "ETH",
      "totalQuota": "11.58000000",
      "productName": null,
      "baseAsset": "ETH",
      "quoteAsset": "USDT",
      "money": null,
      "userId": 35345229,
      "email": null
    },
    {
      "tradeId": 254424784,
      "price": "1159.00",
      "time": 1610612501000,
      "symbol": "ETHUSDT",
      "side": "BUY",
      "activeBuy": false,
      "realPnl": 0,
      "qty": "0.01000",
      "fee": "0.00001000",
      "feeAsset": "ETH",
      "totalQuota": "11.59000000",
      "productName": null,
      "baseAsset": "ETH",
      "quoteAsset": "USDT",
      "money": null,
      "userId": 35345229,
      "email": null
    },
    {
      "tradeId": 254421447,
      "price": "1160.00",
      "time": 1610612310000,
      "symbol": "ETHUSDT",
      "side": "BUY",
      "activeBuy": false,
      "realPnl": 0,
      "qty": "0.01000",
      "fee": "0.00001000",
      "feeAsset": "ETH",
      "totalQuota": "11.60000000",
      "productName": null,
      "baseAsset": "ETH",
      "quoteAsset": "USDT",
      "money": null,
      "userId": 35345229,
      "email": null
    },
    {
      "tradeId": 254420742,
      "price": "1161.00",
      "time": 1610612290000,
      "symbol": "ETHUSDT",
      "side": "BUY",
      "activeBuy": false,
      "realPnl": 0,
      "qty": "0.01000",
      "fee": "0.00001000",
      "feeAsset": "ETH",
      "totalQuota": "11.61000000",
      "productName": null,
      "baseAsset": "ETH",
      "quoteAsset": "USDT",
      "money": null,
      "userId": 35345229,
      "email": null
    },
    {
      "tradeId": 254419087,
      "price": "1162.00",
      "time": 1610612231000,
      "symbol": "ETHUSDT",
      "side": "BUY",
      "activeBuy": false,
      "realPnl": 0,
      "qty": "0.01000",
      "fee": "0.00001000",
      "feeAsset": "ETH",
      "totalQuota": "11.62000000",
      "productName": null,
      "baseAsset": "ETH",
      "quoteAsset": "USDT",
      "money": null,
      "userId": 35345229,
      "email": null
    },
    {
      "tradeId": 254418649,
      "price": "1163.00",
      "time": 1610612224000,
      "symbol": "ETHUSDT",
      "side": "BUY",
      "activeBuy": false,
      "realPnl": 0,
      "qty": "0.01000",
      "fee": "0.00001000",
      "feeAsset": "ETH",
      "totalQuota": "11.63000000",
      "productName": null,
      "baseAsset": "ETH",
      "quoteAsset": "USDT",
      "money": null,
      "userId": 35345229,
      "email": null
    }
  ],
  "total": 152,
  "success": true
}
